design_practice/7week/7week/7week.srcs/sources_1/new/seq_detector.v

//////////////////////////////////////////////////////////////////////////////////
// Company: 
// Engineer: 
// 
// Create Date: 2025/04/22 06:13:07
// Design Name: 
// Module Name: seq_detector
// Project Name: 
// Target Devices: 
// Tool Versions: 
// Description: 
// 
// Dependencies: 
// 
// Revision:
// Revision 0.01 - File Created
// Additional Comments:
// 
//////////////////////////////////////////////////////////////////////////////////

`timescale 1ns/1ps

module seq_detector (
    input  wire clk,      // 시스템 클럭 
    input  wire rstn,     // 비동기식 액티브 Low 리셋
    input  wire w100,     // 100원 동전 입력 
    input  wire btn,      // 버튼 입력 
    output reg  sale,     // 출력  
    output reg  ret       // 돈 반환 
);

    // 상태 부호화 (
    parameter S0   = 2'd0;   // 0원 상태
    parameter S100 = 2'd1;   // 100원 상태
    parameter S200 = 2'd2;   // 200원 상태
    parameter S300 = 2'd3;   // 300원 상태

    // 현재 상태, 다음 상태 레지스터
    reg [1:0] cst, nst;

    // 다음 사이클에 출력할 sale, ret 펄스
    reg       sale_nxt, ret_nxt;

    // 상태 및 출력 레지스터 업데이트 (순차 블록)
    always @(posedge clk or negedge rstn) begin
        if (!rstn) begin
            // 리셋 시 초기 상태 및 출력 클리어
            cst  <= S0;
            sale <= 1'b0;
            ret  <= 1'b0;
        end
        else begin
            // 정상 작동 시 다음 상태, 다음 출력으로 갱신
            cst  <= nst;        // 다음 상태 등록
            sale <= sale_nxt;   // 음료 출력 등록
            ret  <= ret_nxt;    // 돈 반환 등록
        end
    end

    // 다음 상태 및 출력 결정 로직 (조합 블록)
    always @(*) begin
        // 기본값 설정: 변화 없음, 펄스 출력 0
        nst      = cst;
        sale_nxt = 1'b0;
        ret_nxt  = 1'b0;

        case (cst)

            // S0: 0원 상태
            S0: begin
                if (w100) begin
                    // 100원 투입 → 100원 상태로
                    nst = S100;
                end
                else if (btn) begin
                    // 버튼만 눌러도 잔돈 없으므로 무시
                    nst = S0;
                end
            end


            // S100: 100원 상태
            S100: begin
                if (w100) begin
                    // 추가 100원 투입 → 200원 상태로
                    nst = S200;
                end
                else if (btn) begin
                    // 버튼 → 100원 반환 후 0원 상태로
                    nst     = S0;
                    ret_nxt = 1'b1;
                end
            end


            // S200: 200원 상태
            S200: begin
                if (w100) begin
                    // 추가 100원 투입 → 300원 이상 상태로
                    nst = S300;
                end
                else if (btn) begin
                    // 버튼 → 200원 전액 반환 후 0원 상태로
                    nst     = S0;
                    ret_nxt = 1'b1;
                end
            end

            // S300: 300원 이상 상태
            S300: begin
                if (w100) begin
                    // 300원 이상 초과 동전 투입 시 초과분 바로 반환
                    nst     = S300;
                    ret_nxt = 1'b1;
                end
                else if (btn) begin
                    // 버튼 → 음료 출력, 잔액 0원으로
                    nst      = S0;
                    sale_nxt = 1'b1;
                end
            end

            // 디폴트: 안전을 위해 0원 상태로
            default: begin
                nst = S0;
            end

        endcase
    end

endmodule

design_practice/7week/7week/7week.srcs/sim_1/new/tb_seq_detector.v
`timescale 1ns / 1ps
//////////////////////////////////////////////////////////////////////////////////
// Company: 
// Engineer: 
// 
// Create Date: 2025/04/22 06:13:23
// Design Name: 
// Module Name: tb_seq_detector
// Project Name: 
// Target Devices: 
// Tool Versions: 
// Description: 
// 
// Dependencies: 
// 
// Revision:
// Revision 0.01 - File Created
// Additional Comments:
// 
//////////////////////////////////////////////////////////////////////////////////

`timescale 1ns/1ps
module tb_seq_detector;
    reg  clk  = 0;
    reg  rstn = 0;
    reg  w100 = 0;
    reg  btn  = 0;
    wire sale;
    wire ret;

    seq_detector UUT (
        .clk  (clk),
        .rstn (rstn),
        .w100 (w100),
        .btn  (btn),
        .sale (sale),
        .ret  (ret)
    );

    //10‑ns 클록
    always #5 clk = ~clk;      // 100 MHz

    initial begin
        //0~12 ns 구간
        #12  rstn = 1;         // 다음 상승에지(15 ns) 전에 reset 해제

        //첫 번째 100원 : 18~27 ns
        #6   w100 = 1;         // 지금 시각 18 ns
        #9   w100 = 0;         // 27 ns → 25 ns 상승에지만 통과

        //두 번째 100원 : 45~54 n
        #18  w100 = 1;
        #9   w100 = 0;

        //세 번째 100원 + 버튼 동시 : 72~81 ns 
        #18  begin w100 = 1; btn = 1; end
        #9   begin w100 = 0; btn = 0; end

        //네 번째 100원 : 99~108 ns
        #18  w100 = 1;
        #9   w100 = 0;

        //버튼 한번 더 : 126~135 ns
        #18  btn = 1;
        #9   btn = 0;

        #50  $finish;
    end

    initial begin
        $monitor("T=%0t | w100=%b btn=%b | sale=%b ret=%b",
                  $time, w100, btn, sale, ret);
        $dumpfile("tb_seq_detector.vcd");
        $dumpvars(0,tb_seq_detector);
    end
endmodule

design_practice/7week/7week/7week.sim/sim_1/behav/xsim/tb_seq_detector.vcd
$date
   Tue Apr 22 20:49:52 2025
$end
$version
  2019.2
$end
$timescale
  1ps
$end
$scope module tb_seq_detector $end
$var reg 1 ! clk $end
$var reg 1 " rstn $end
$var reg 1 # w100 $end
$var reg 1 $ btn $end
$var wire 1 % sale $end
$var wire 1 & ret $end
$scope module UUT $end
$var wire 1 ' clk $end
$var wire 1 ( rstn $end
$var wire 1 ) w100 $end
$var wire 1 * btn $end
$var reg 1 + sale $end
$var reg 1 , ret $end
$var reg 2 - cst [1:0] $end
$var reg 2 . nst [1:0] $end
$var reg 1 / sale_nxt $end
$var reg 1 0 ret_nxt $end
$var parameter 2 1 S0 [1:0] $end
$var parameter 2 2 S100 [1:0] $end
$var parameter 2 3 S200 [1:0] $end
$var parameter 2 4 S300 [1:0] $end
$upscope $end
$upscope $end
$enddefinitions $end
#0
$dumpvars
0!
0"
0#
0$
0%
0&
0'
0(
0)
0*
0+
0,
b0 -
b0 .
0/
00
b0 1
b1 2
b10 3
b11 4
$end
#5000
1!
1'
#10000
0!
0'
#12000
1"
1(
#15000
1!
1'
#18000
1#
1)
b1 .
#20000
0!
0'
#25000
1!
1'
b1 -
b10 .
#27000
0#
0)
b1 .
#30000
0!
0'
#35000
1!
1'
#40000
0!
0'
#45000
1!
1#
1'
1)
b10 -
b11 .
#50000
0!
0'
#54000
0#
0)
b10 .
#55000
1!
1'
#60000
0!
0'
#65000
1!
1'
#70000
0!
0'
#72000
1#
1$
1)
1*
b11 .
#75000
1!
1'
b11 -
10
#80000
0!
0'
#81000
0#
0$
0)
0*
00
#85000
1!
1'
#90000
0!
0'
#95000
1!
1'
#99000
1#
1)
10
#100000
0!
0'
#105000
1!
1&
1'
1,
#108000
0#
0)
00
#110000
0!
0'
#115000
1!
0&
1'
0,
#120000
0!
0'
#125000
1!
1'
#126000
1$
1*
b0 .
1/
#130000
0!
0'
#135000
1!
0$
1'
0*
b11 .
0/
